karrio/mappers/landmark/__init__.py
karrio/mappers/landmark/mapper.py
karrio/mappers/landmark/proxy.py
karrio/mappers/landmark/settings.py
karrio/plugins/landmark/__init__.py
karrio/providers/landmark/__init__.py
karrio/providers/landmark/error.py
karrio/providers/landmark/services.csv
karrio/providers/landmark/tracking.py
karrio/providers/landmark/units.py
karrio/providers/landmark/utils.py
karrio/providers/landmark/shipment/__init__.py
karrio/providers/landmark/shipment/cancel.py
karrio/providers/landmark/shipment/create.py
karrio/schemas/landmark/__init__.py
karrio/schemas/landmark/cancel_request.py
karrio/schemas/landmark/cancel_response.py
karrio/schemas/landmark/error_response.py
karrio/schemas/landmark/import_request.py
karrio/schemas/landmark/import_response.py
karrio/schemas/landmark/ship_request.py
karrio/schemas/landmark/ship_response.py
karrio/schemas/landmark/track_request.py
karrio/schemas/landmark/track_response.py
karrio_landmark-2026.1.4.dist-info/METADATA
karrio_landmark-2026.1.4.dist-info/WHEEL
karrio_landmark-2026.1.4.dist-info/entry_points.txt
karrio_landmark-2026.1.4.dist-info/top_level.txt
karrio_landmark-2026.1.4.dist-info/RECORD
